__init__.py
jacpy/__init__.py
jacpy/geometry/__init__.py
jacpy/geometry/geoUtils.py
jacpy/hash/__init__.py
jacpy/hash/hashUtils.py
jacpy/io/__init__.py
jacpy/io/ioUtils.py
jacpy/time/TimedSampleStore.py
jacpy/time/__init__.py
jacpy-0.0.11.dist-info/licenses/LICENSE
jacpy-0.0.11.dist-info/METADATA
jacpy-0.0.11.dist-info/WHEEL
jacpy-0.0.11.dist-info/top_level.txt
jacpy-0.0.11.dist-info/RECORD
