Metadata-Version: 2.4
Name: jacpy
Version: 0.0.11
Summary: A python utility project
Author-email: Alberto Anguita <alberto.anguita@gmail.com>
Project-URL: Homepage, https://github.com/albertoanguita/jacpy
Project-URL: Issues, https://github.com/albertoanguita/jacpy/issues
Classifier: Programming Language :: Python :: 3
Classifier: License :: OSI Approved :: MIT License
Classifier: Operating System :: OS Independent
Requires-Python: >=3.8
License-File: LICENSE
Dynamic: license-file
